paladin/_ODESolution.py
paladin/__init__.py
paladin/_algo_factory.py
paladin/_eom_scipy_cr3bp.py
paladin/_eom_scipy_nbody.py
paladin/_gsl_event.py
paladin/_heyoka_nbody.py
paladin/_newtonraphson.py
paladin/_nodes_helper.py
paladin/_perturbations.py
paladin/_plotter.py
paladin/_propagate_gsl.py
paladin/_propagator_gsl_mee.py
paladin/_propagator_gsl_nbody.py
paladin/_propagator_scipy_cr3bp.py
paladin/_propagator_scipy_nbody.py
paladin/_symbolic_jacobians.py
paladin/_transformation.py
paladin/_udp_FullEphemerisTransition.py
paladin/_wrap_propagator.py
paladin/eoms/_eom_cr3bp.py
paladin/eoms/_eom_mee.py
paladin/eoms/_eom_nbody.py
paladin/eoms/_eom_nbody_srp.py
paladin/symbolic_jacobians/_jac_nbody.py
paladin/symbolic_jacobians/_jac_nbody_srp.py
paladin/symbolic_jacobians/_symbolic_utils.py
spacecraft_paladin-0.1.7.dist-info/licenses/LICENSE
spacecraft_paladin-0.1.7.dist-info/METADATA
spacecraft_paladin-0.1.7.dist-info/WHEEL
spacecraft_paladin-0.1.7.dist-info/top_level.txt
spacecraft_paladin-0.1.7.dist-info/RECORD
