Metadata-Version: 2.4
Name: spacecraft-paladin
Version: 0.1.7
Summary: high-fidelity spaceraft dynamics propagator
Home-page: https://github.com/Yuricst/paladin
Author: Yuri Shimane
Author-email: yuri.shimane@gatech.edu
License: MIT License
Keywords: astrodynamics
Classifier: Programming Language :: Python :: 3.10
Classifier: Programming Language :: Python :: 3.11
Classifier: Programming Language :: Python :: 3.12
Classifier: Programming Language :: Python :: 3.13
Classifier: Programming Language :: Python :: 3.14
License-File: LICENSE
Requires-Dist: numpy>=1.26.4
Requires-Dist: numba>=0.54.0
Requires-Dist: matplotlib>=3.8.4
Requires-Dist: scipy>=1.13.0
Requires-Dist: spiceypy>=6.0.0
Requires-Dist: sympy>=1.12
Requires-Dist: pygsl>=2.3.3
Dynamic: author
Dynamic: author-email
Dynamic: classifier
Dynamic: description
Dynamic: description-content-type
Dynamic: home-page
Dynamic: keywords
Dynamic: license
Dynamic: license-file
Dynamic: requires-dist
Dynamic: summary
